{
    "header": {
        "grc": "Ὅροι",
        "lat": "Definitiones",
        "eng": "Definitions"
    },
    "definitions": [
        {
            "number": {
                "ordinal": {
                    "grc": "πρῶτος",
                    "lat": "Prima",
                    "eng": "First"
                    },
                "symbol": {
                    "grc": "α΄",
                    "lat": "I",
                    "eng": "1"
                }
            },
            "text": {
                "grc": "σημεῖόν ἐστιν, οὗ μέρος οὐθέν.",
                "lat": "Punctum est, cuius pars nulla est.",
                "eng": "A point is that which has no part."
            },
            "commentary": {
                "grc": "",
                "lat": "",
                "eng": ""
            }
        },
        {
            "number": {
                "ordinal": {
                    "grc": "δεύτερος",
                    "lat": "Secunda",
                    "eng": "Second"
                    },
                "symbol": {
                    "grc": "β΄",
                    "lat": "II",
                    "eng": "2"
                }
            },
            "text": {
                "grc": "γραμμὴ δὲ μῆκος ἀπλατές.",
                "lat": "Linea autem sine latitudine longitudo.",
                "eng": "A line is breadthless length."
            },
            "commentary": {
                "grc": "",
                "lat": "",
                "eng": ""
            }
        },
        {
            "number": {
                "ordinal": {
                    "grc": "τρίτος",
                    "lat": "Tertia",
                    "eng": "Third"
                    },
                "symbol": {
                    "grc": "γ΄",
                    "lat": "III",
                    "eng": "3"
                }
            },
            "text": {
                "grc": "γραμμῆς δὲ πέρατα σημεῖα.",
                "lat": "Lineae autem extrema puncta.",
                "eng": "The extremities of a line are points."
            },
            "commentary": {
                "grc": "",
                "lat": "",
                "eng": ""
            }
        },
        {
            "number": {
                "ordinal": {
                    "grc": "τέταρτος",
                    "lat": "Quarta",
                    "eng": "Fourth"
                    },
                "symbol": {
                    "grc": "δ΄",
                    "lat": "IV",
                    "eng": "4"
                }
            },
            "text": {
                "grc": "εὐθεῖα γραμμή ἐστιν, ἥτις ἐξ ἴσου τοῖς ἐφ' ἑαυτῆς σημείοις κεῖται.",
                "lat": "Recta linea est, quaecunque ex aequo punctis in ea sitis iacet.",
                "eng": "A straight line is a line which lies evenly with the points on itself."
            },
            "commentary": {
                "grc": "",
                "lat": "",
                "eng": ""
            }
        },
        {
            "number": {
                "ordinal": {
                    "grc": "πέμπτος",
                    "lat": "Quinta",
                    "eng": "Fifth"
                    },
                "symbol": {
                    "grc": "ε΄",
                    "lat": "V",
                    "eng": "5"
                }
            },
            "text": {
                "grc": "ἐπιφάνεια δέ ἐστιν, ὃ μῆκος καὶ πλάτος μόνον ἔχει.",
                "lat": "Superficiem autem est, quod longitudinem et latitudinem solum habet.",
                "eng": "A surface is that which has length and breadth only."
            },
            "commentary": {
                "grc": "",
                "lat": "",
                "eng": ""
            }
        },
        {
            "number": {
                "ordinal": {
                    "grc": "ἕκτος",
                    "lat": "Sexta",
                    "eng": "Sixth"
                    },
                "symbol": {
                    "grc": "ς΄",
                    "lat": "VI",
                    "eng": "6"
                }
            },
            "text": {
                "grc": "ἐπιφανείας δὲ πέρατα γραμμαί.",
                "lat": "Superficiei autem extrema lineae sunt.",
                "eng": "The extremities of a surface are lines."
            },
            "commentary": {
                "grc": "",
                "lat": "",
                "eng": ""
            }
        },
        {
            "number": {
                "ordinal": {
                    "grc": "ἕβδομος",
                    "lat": "Septima",
                    "eng": "Seventh"
                    },
                "symbol": {
                    "grc": "ζ΄",
                    "lat": "VII",
                    "eng": "7"
                }
            },
            "text": {
                "grc": "ἐπίπεδος ἐπιφάνειά ἐστιν, ἥτις ἐξ ἴσου ταῖς ἐφ' ἑαυτῆς εὐθείαις κεῖται.",
                "lat": "Plana superficies est, quaecunque ex aequo rectis in ea sitis iacet.",
                "eng": "A plane surface is a surface which lies evenly with the straight lines on itself."
            },
            "commentary": {
                "grc": "",
                "lat": "",
                "eng": ""
            }
        },
        {
            "number": {
                "ordinal": {
                    "grc": "ὄγδοος",
                    "lat": "Octava",
                    "eng": "Eighth"
                    },
                "symbol": {
                    "grc": "η΄",
                    "lat": "VIII",
                    "eng": "8"
                }
            },
            "text": {
                "grc": "ἐπίπεδος δὲ γωνία ἐστὶν ἡ ἐν ἐπιπέδῳ δύο γραμμῶν ἁπτομένων ἀλλήλων καὶ μὴ ἐπ' εὐθείας κειμένων πρὸς ἀλλήλας τῶν γραμμῶν κλίσις.",
                "lat": "Planus autem angulus est duabus lineis in plano se tangentibus nec in eadem recta positis alterius lineae ad alteram inclinatio.",
                "eng": "A plane angle is the inclination to one another of two lines in a plane which meet one another and do not lie in a straight line."
            },
            "commentary": {
                "grc": "",
                "lat": "",
                "eng": ""
            }
        },
        {
            "number": {
                "ordinal": {
                    "grc": "ἐνατος",
                    "lat": "Nona",
                    "eng": "Ninth"
                    },
                "symbol": {
                    "grc": "θ΄",
                    "lat": "IX",
                    "eng": "9"
                }
            },
            "text": {
                "grc": "ὅταν δὲ αἱ περιέχουσαι τὴν γωνίαν γραμμαὶ εὐθεῖαι ὦσιν, εὐθύγραμμος καλεῖται ἡ γωνία.",
                "lat": "Ubi vero lineae angulum continentes rectae sunt, rectilineus adpellatur angulus.",
                "eng": "And when the lines containing the angle are straight, the angle is called rectilineal."
            },
            "commentary": {
                "grc": "",
                "lat": "",
                "eng": ""
            }
        },
        {
            "number": {
                "ordinal": {
                    "grc": "δέκατος",
                    "lat": "Decima",
                    "eng": "Tenth"
                    },
                "symbol": {
                    "grc": "ι΄",
                    "lat": "X",
                    "eng": "10"
                }
            },
            "text": {
                "grc": "ὅταν δὲ εὐθεῖα ἐπ' εὐθεῖαν σταθεῖσα τὰς ἐφεξῆς γωνίας ἴσας ἀλλήλαις ποιῇ, ὀρθὴ ἑκατέρα τῶν ἴσων γωνιῶν ἐστι, καὶ ἡ ἐφεστηκυῖα εὐθεῖα κάθετος καλεῖται, ἐφ' ἣν ἐφέστηκεν.",
                "lat": "Ubi vero recta super rectam lineam erecta angulos deinceps positos inter se aequales efficit, rectus est uterque angulus aequalis, et recta linea erecta perpendicularis adpellatur ad eam, super quam erecta est.",
                "eng": "When a straight line set up on a straight line makes the adjacent angles equal to one another, each of the equal angles is right, and the straight line standing on the other is called a perpendicular to that on which it stands."
            },
            "commentary": {
                "grc": "",
                "lat": "",
                "eng": ""
            }
        },
        {
            "number": {
                "ordinal": {
                    "grc": "ἑνδέκατος",
                    "lat": "Undecima",
                    "eng": "Eleventh"
                    },
                "symbol": {
                    "grc": "ια΄",
                    "lat": "XI",
                    "eng": "11"
                }
            },
            "text": {
                "grc": "ἀμβλεῖα γωνία ἐστὶν ἡ μείζων ὀρθῆς.",
                "lat": "Obtusus angulus est, qui maior est recto.",
                "eng": "An obtuse angle is an angle greater than a right angle."
            },
            "commentary": {
                "grc": "",
                "lat": "",
                "eng": ""
            }
        },
        {
            "number": {
                "ordinal": {
                    "grc": "δωδέκατος",
                    "lat": "Duodecima",
                    "eng": "Twelfth"
                    },
                "symbol": {
                    "grc": "ιβ΄",
                    "lat": "XII",
                    "eng": "12"
                }
            },
            "text": {
                "grc": "ὀξεῖα δὲ ἡ ἐλάσσων ὀρθῆς.",
                "lat": "Acutus vero, qui minor est recto.",
                "eng": "An acute angle is an angle less than a right angle."
            },
            "commentary": {
                "grc": "",
                "lat": "",
                "eng": ""
            }
        },
        {
            "number": {
                "ordinal": {
                    "grc": "δέκατος τρίτος",
                    "lat": "Tertia Decima",
                    "eng": "Thirteenth"
                    },
                "symbol": {
                    "grc": "ιγ΄",
                    "lat": "XIII",
                    "eng": "13"
                }
            },
            "text": {
                "grc": "ὅρος ἐστίν, ὅ τινός ἐστι πέρας.",
                "lat": "Terminus est, quod alicuius rei extremum est.",
                "eng": "A boundary is that which is an extremity of anything."
            },
            "commentary": {
                "grc": "",
                "lat": "",
                "eng": ""
            }
        },
        {
            "number": {
                "ordinal": {
                    "grc": "δέκατος τέταρτος",
                    "lat": "Quarta Decima",
                    "eng": "Fourteenth"
                    },
                "symbol": {
                    "grc": "ιδ΄",
                    "lat": "XIV",
                    "eng": "14"
                }
            },
            "text": {
                "grc": "σχῆμά ἐστι τὸ ὑπό τινος ἤ τινων ὅρων περιεχόμενον.",
                "lat": "Figura est, quod aliquo vel aliquibus terminis comprehenditur.",
                "eng": "A figure is that which is contained by any boundary or boundaries."
            },
            "commentary": {
                "grc": "",
                "lat": "",
                "eng": ""
            }
        },
        {
            "number": {
                "ordinal": {
                    "grc": "δέκατος πέμπτος",
                    "lat": "Quinta Decima",
                    "eng": "Fifteenth"
                    },
                "symbol": {
                    "grc": "ιε΄",
                    "lat": "XV",
                    "eng": "15"
                }
            },
            "text": {
                "grc": "κύκλος ἐστὶ σχῆμα ἐπίπεδον ὑπὸ μιᾶς γραμμῆς περιεχόμενον [ἣ καλεῖται περιφέρεια], πρὸς ἣν ἀφ' ἑνὸς σημείου τῶν ἐντὸς τοῦ σχήματος κειμένων πᾶσαι αἱ προσπίπτουσαι εὐθεῖαι [πρὸς τὴν τοῦ κύκλου περιφέρειαν] ἴσαι ἀλλήλαις εἰσίν.",
                "lat": "Circulus est figura plana una linea comprehensa, ad quam quae ab uno puncto intra figuram posito educuntur rectae omnes aequales sunt.",
                "eng": "A circle is a plane figure contained by one line such that all the straight lines falling upon it from one point among those lying within the figure are equal to one another."
            },
            "commentary": {
                "grc": "",
                "lat": "",
                "eng": ""
            }
        },
        {
            "number": {
                "ordinal": {
                    "grc": "δέκατος ἕκτος",
                    "lat": "Sexta Decima",
                    "eng": "Sixteenth"
                    },
                "symbol": {
                    "grc": "ις΄",
                    "lat": "XVI",
                    "eng": "16"
                }
            },
            "text": {
                "grc": "κέντρον δὲ τοῦ κύκλου τὸ σημεῖον καλεῖται.",
                "lat": "Centrum autem circuli punctum illud adpellatur.",
                "eng": "And the point is called the centre of the circle."
            },
            "commentary": {
                "grc": "",
                "lat": "",
                "eng": ""
            }
        },
        {
            "number": {
                "ordinal": {
                    "grc": "δέκατος ἕβδομος",
                    "lat": "Septima Decima",
                    "eng": "Seventeenth"
                    },
                "symbol": {
                    "grc": "ιζ΄",
                    "lat": "XVII",
                    "eng": "17"
                }
            },
            "text": {
                "grc": "διάμετρος δὲ τοῦ κύκλου ἐστὶν εὐθεῖά τις διὰ τοῦ κέντρου ἠγμένη καὶ περατουμένη ἐφ' ἑκάτερα τὰ μέρη ὑπὸ τῆς τοῦ κύκλου περιφερείας, ἥτις καὶ δίχα τέμνει τὸν κύκλον.",
                "lat": "Diametrus autem circuli recta quaedam est linea per centrum ducta et terminata utrimque ambitu circuli, quae quidem linea circulum in duas partes aequales dividit.",
                "eng": "A diameter of the circle is any straight line drawn through the center and terminated in both directions by the circumference of the circle, and such a straight line also bisects the circle."
            },
            "commentary": {
                "grc": "",
                "lat": "",
                "eng": ""
            }
        },
        {
            "number": {
                "ordinal": {
                    "grc": "δέκατος ὄγδοος",
                    "lat": "Duodevicensima",
                    "eng": "Eighteenth"
                    },
                "symbol": {
                    "grc": "ιη΄",
                    "lat": "XVIII",
                    "eng": "18"
                }
            },
            "text": {
                "grc": "ἡμικύκλιον δέ ἐστι τὸ περιεχόμενον σχῆμα ὑπό τε τῆς διαμέτρου καὶ τῆς ἀπολαμβανομένης ὑπ' αὐτῆς περιφερείας. κέντρον δὲ τοῦ ἡμικυκλίου τὸ αὐτό, ὃ καὶ τοῦ κύκλου ἐστίν.",
                "lat": "Semicirculus autem ea est figura, quae diametro et arcu ab ea absciso comprehenditur. Centro vero semicirculi idem est, quod ipsius est circuli.",
                "eng": "A semicircle is the figure contained by the diameter and the circumference cut off by it. And the center of the semicircle is the same as that of the circle."
            },
            "commentary": {
                "grc": "",
                "lat": "",
                "eng": ""
            }
        },
        {
            "number": {
                "ordinal": {
                    "grc": "δέκατος ἔνατος",
                    "lat": "Undevicensima",
                    "eng": "Nineteenth"
                    },
                "symbol": {
                    "grc": "ιθ΄",
                    "lat": "XIX",
                    "eng": "19"
                }
            },
            "text": {
                "grc": "σχήματα εὐθύγραμμά ἐστι τὰ ὑπὸ εὐθειῶν περιεχόμενα, τρίπλευρα μὲν τὰ ὑπὸ τριῶν, τετράπλευρα δὲ τὰ ὑπὸ τεσσάρων, πολύπλευρα δὲ τὰ ὑπὸ πλειόνων ἢ τεσσάρων εὐθειῶν περιεχόμενα.",
                "lat": "Figurae rectilineae sunt, quae rectis lineis comprehenduntur, trilaterae quae tribus, quadrilaterae quae quattuor, multilaterae quae plus quam quattor rectis comprehenduntur.",
                "eng": "Rectilineal figures are those which are contained by straight lines, trilateral figures being those contained by three, quadrilateral those contained by four, and multilateral those contained by more than four straight lines."
            },
            "commentary": {
                "grc": "",
                "lat": "",
                "eng": ""
            }
        },
        {
            "number": {
                "ordinal": {
                    "grc": "εἰκοστός",
                    "lat": "Vicensima",
                    "eng": "Twentieth"
                    },
                "symbol": {
                    "grc": "κ΄",
                    "lat": "XX",
                    "eng": "20"
                }
            },
            "text": {
                "grc": "τῶν δὲ τριπλεύρων σχημάτων ἰσόπλευρον μὲν τρίγωνόν ἐστι τὸ τὰς τρεῖς ἴσας ἔχον πλευράς, ἰσοσκελὲς δὲ τὸ τὰς δύο μόνας ἴσας ἔχον πλευράς, σκαληνὸν δὲ τὸ τὰς τρεῖς ἀνίσους ἔχον πλευράς.",
                "lat": "Ex figuris autem trilateris aequilaterus triangulus est, qui tria latera sua aequalia habet, aequicrurius vero, qui duo sola aequalia habet, scalenus autem, qui tria latera sua inaequalia habet.",
                "eng": "Of trilateral figures, an equilateral triangle is that which has its three sides equal, an isosceles triangle that which has two of its sides alone equal, and a scalene triangle that which has its three sides unequal."
            },
            "commentary": {
                "grc": "",
                "lat": "",
                "eng": ""
            }
        },
        {
            "number": {
                "ordinal": {
                    "grc": "εἰκοστὸς πρῶτος",
                    "lat": "Vicensima Prima",
                    "eng": "Twenty First"
                    },
                "symbol": {
                    "grc": "κα΄",
                    "lat": "XXI",
                    "eng": "21"
                }
            },
            "text": {
                "grc": "ἔτι δὲ τῶν τριπλεύρων σχημάτων ὀρθογώνιον μὲν τρίγωνόν ἐστι τὸ ἔχον ὀρθὴν γωνίαν, ἀμβλυγώνιον δὲ τὸ ἔχον ἀμβλεῖαν γωνίαν, ὀξυγώνιον δὲ τὸ τὰς τρεῖς ὀξείας ἔχον γωνίας.",
                "lat": "Praeterea vero ex figuris trilateris rectangulus triangulus est, qui rectum angulum habet, obtusiangulus, qui obtusum habet, acutiangulus autem, qui tres angulos suos acutos habet.",
                "eng": "Further, of trilateral figures, a right-angled triangle is that which has a right angle, an obtuse-angled triangle that which has an obtuse angle, and an acute-angled triangle that which has its three angles acute."
            },
            "commentary": {
                "grc": "",
                "lat": "",
                "eng": ""
            }
        },
        {
            "number": {
                "ordinal": {
                    "grc": "εἰκοστὸς δεύτερος",
                    "lat": "Vicensima Secunda",
                    "eng": "Twenty Second"
                    },
                "symbol": {
                    "grc": "κβ΄",
                    "lat": "XXII",
                    "eng": "22"
                }
            },
            "text": {
                "grc": "τῶν δὲ τετραπλεύρων σχημάτων τετράγωνον μέν ἐστιν, ὃ ἰσόπλευρόν τέ ἐστι καὶ ὀρθογώνιον, ἑτερόμηκες δέ, ὃ ὀρθογώνιον μέν, οὐκ ἰσόπλευρον δέ, ῥόμβος δέ, ὃ ἰσόπλευρον μέν, οὐκ ὀρθογώνιον δέ, ῥομβοειδὲς δὲ τὸ τὰς ἀπεναντίον πλευράς τε καὶ γωνίας ἴσας ἀλλήλαις ἔχον, ὃ οὔτε ἰσόπλευρόν ἐστιν οὔτε ὀρθογώνιον: τὰ δὲ παρὰ ταῦτα τετράπλευρα τραπέζια καλείσθω.",
                "lat": "Ex quadrilateris autem figuris quadratum est, quod simul aequilaterum est et rectangulum, parte altera longius est, quod rectangulum est neque uero aequilaterum, rhombus autem, quod aequilaterum est neque vero rectangulum, rhomboides autem, quod latera simul et angulos inter se opposita aequalia habet, sed neque aequilaterum est neque rectangulum; reliqua autem praeter haec quadrilatera trapezia adpellentur.",
                "eng": "Of quadrilateral figures, a square is that which is both equilateral and right-angled; an oblong that which is right-angled but not equilateral; a rhombus that which is equilateral but not right-angled; and a rhomboid that which has its opposite sides and angles equal to one another but is neither equilateral nor right-angled. And let quadrilaterals other than these be called trapezia."
            },
            "commentary": {
                "grc": "",
                "lat": "",
                "eng": ""
            }
        },
        {
            "number": {
                "ordinal": {
                    "grc": "εἰκοστὸς τρίτος",
                    "lat": "Vicensima Tertia",
                    "eng": "Twenty Third"
                    },
                "symbol": {
                    "grc": "κγ΄",
                    "lat": "XXIII",
                    "eng": "23"
                }
            },
            "text": {
                "grc": "παράλληλοί εἰσιν εὐθεῖαι, αἵτινες ἐν τῷ αὐτῷ ἐπιπέδῳ οὖσαι καὶ ἐκβαλλόμεναι εἰς ἄπειρον ἐφ' ἑκάτερα τὰ μέρη ἐπὶ μηδέτερα συμπίπτουσιν ἀλλήλαις.",
                "lat": "Parallelae sunt lineae, quae in eodem plano positae et in utramque partem productae in infinitum in neutra parte concurrunt.",
                "eng": "Parallel straight lines are straight lines which, being in the same plane and being produced indefinitely in both directions do not meet one another in either direction."
            },
            "commentary": {
                "grc": "",
                "lat": "",
                "eng": ""
            }
        }
    ]
}
